azure/mgmt/recoveryservices/__init__.py
azure/mgmt/recoveryservices/_configuration.py
azure/mgmt/recoveryservices/_patch.py
azure/mgmt/recoveryservices/_recovery_services_client.py
azure/mgmt/recoveryservices/_serialization.py
azure/mgmt/recoveryservices/_vendor.py
azure/mgmt/recoveryservices/_version.py
azure/mgmt/recoveryservices/py.typed
azure/mgmt/recoveryservices/aio/__init__.py
azure/mgmt/recoveryservices/aio/_configuration.py
azure/mgmt/recoveryservices/aio/_patch.py
azure/mgmt/recoveryservices/aio/_recovery_services_client.py
azure/mgmt/recoveryservices/aio/_vendor.py
azure/mgmt/recoveryservices/aio/operations/__init__.py
azure/mgmt/recoveryservices/aio/operations/_operations.py
azure/mgmt/recoveryservices/aio/operations/_patch.py
azure/mgmt/recoveryservices/aio/operations/_private_link_resources_operations.py
azure/mgmt/recoveryservices/aio/operations/_recovery_services_client_operations.py
azure/mgmt/recoveryservices/aio/operations/_recovery_services_operations.py
azure/mgmt/recoveryservices/aio/operations/_registered_identities_operations.py
azure/mgmt/recoveryservices/aio/operations/_replication_usages_operations.py
azure/mgmt/recoveryservices/aio/operations/_usages_operations.py
azure/mgmt/recoveryservices/aio/operations/_vault_certificates_operations.py
azure/mgmt/recoveryservices/aio/operations/_vault_extended_info_operations.py
azure/mgmt/recoveryservices/aio/operations/_vaults_operations.py
azure/mgmt/recoveryservices/models/__init__.py
azure/mgmt/recoveryservices/models/_models_py3.py
azure/mgmt/recoveryservices/models/_patch.py
azure/mgmt/recoveryservices/models/_recovery_services_client_enums.py
azure/mgmt/recoveryservices/operations/__init__.py
azure/mgmt/recoveryservices/operations/_operations.py
azure/mgmt/recoveryservices/operations/_patch.py
azure/mgmt/recoveryservices/operations/_private_link_resources_operations.py
azure/mgmt/recoveryservices/operations/_recovery_services_client_operations.py
azure_mgmt_recoveryservices-3.0.0.dist-info/LICENSE
azure_mgmt_recoveryservices-3.0.0.dist-info/METADATA
azure_mgmt_recoveryservices-3.0.0.dist-info/WHEEL
azure_mgmt_recoveryservices-3.0.0.dist-info/top_level.txt
azure_mgmt_recoveryservices-3.0.0.dist-info/RECORD
